vibetest/__init__.py
vibetest/agents.py
vibetest/mcp_server.py
vibetest_use-0.1.2.dist-info/licenses/LICENSE
vibetest_use-0.1.2.dist-info/METADATA
vibetest_use-0.1.2.dist-info/WHEEL
vibetest_use-0.1.2.dist-info/entry_points.txt
vibetest_use-0.1.2.dist-info/top_level.txt
vibetest_use-0.1.2.dist-info/RECORD
