Metadata-Version: 2.4
Name: vibetest-use
Version: 0.1.2
Summary: Browser-agent QA swarm with MCP interface for testing AI-generated websites
Author-email: im47cn <dreambt@gmail.com>
License-Expression: MIT
Project-URL: Homepage, https://github.com/im47cn/vibetest-use
Project-URL: Repository, https://github.com/im47cn/vibetest-use
Project-URL: Issues, https://github.com/im47cn/vibetest-use/issues
Keywords: testing,browser,automation,qa,mcp
Classifier: Development Status :: 3 - Alpha
Classifier: Intended Audience :: Developers
Classifier: Programming Language :: Python :: 3
Classifier: Programming Language :: Python :: 3.11
Classifier: Programming Language :: Python :: 3.12
Classifier: Topic :: Software Development :: Testing
Classifier: Topic :: Internet :: WWW/HTTP :: Browsers
Requires-Python: >=3.11
License-File: LICENSE
Requires-Dist: mcp[cli]>=1.0.0
Requires-Dist: browser-use
Requires-Dist: playwright
Requires-Dist: langchain_google_genai
Requires-Dist: langchain_core
Requires-Dist: pydantic
Requires-Dist: screeninfo
Dynamic: license-file
